awsconsurl/__init__.py
awsconsurl/consurl.py
awsconsurl-24.4.4.data/scripts/consurl
awsconsurl-24.4.4.dist-info/LICENSE.txt
awsconsurl-24.4.4.dist-info/METADATA
awsconsurl-24.4.4.dist-info/WHEEL
awsconsurl-24.4.4.dist-info/top_level.txt
awsconsurl-24.4.4.dist-info/RECORD
