Metadata-Version: 2.1
Name: awsconsurl
Version: 24.4.4
Summary: Creates and Opens an AWS console login URL in a Browser
Home-page: https://github.com/Glocktober/consurl
Author: gunville
Author-email: rk13088@yahoo.com
Project-URL: repo, https://github.com/Glocktober/consurl
Project-URL: overview, https://github.com/Glocktober/consurl/blob/main/README.md
Keywords: 'aws'
Classifier: Programming Language :: Python :: 3
Classifier: License :: OSI Approved :: MIT License
Classifier: Operating System :: OS Independent
Classifier: Framework :: Bottle
Requires-Python: >=3.6
License-File: LICENSE.txt
Requires-Dist: boto3 >=1.18.0
Requires-Dist: Requests >=2.26.0
